rdf_uploader/__about__.py
rdf_uploader/__init__.py
rdf_uploader/cli.py
rdf_uploader/endpoints.py
rdf_uploader/file_readers.py
rdf_uploader/uploader.py
rdf_uploader/utils.py
rdf_uploader-0.18.8.dist-info/METADATA
rdf_uploader-0.18.8.dist-info/WHEEL
rdf_uploader-0.18.8.dist-info/entry_points.txt
rdf_uploader-0.18.8.dist-info/licenses/LICENSE
rdf_uploader-0.18.8.dist-info/RECORD
