Metadata-Version: 2.4
Name: rdf-uploader
Version: 0.18.8
Summary: A tool for uploading RDF data to SPARQL endpoints
Project-URL: Homepage, https://github.com/vladistan/rdf-uploader
Project-URL: Bug Tracker, https://github.com/vladistan/rdf-uploader/issues
Author-email: Vlad Korolev <vlad@v-lad.org>
License-Expression: MIT
License-File: LICENSE
Keywords: loader,rdf,tools
Classifier: Development Status :: 3 - Alpha
Classifier: Environment :: Console
Classifier: Intended Audience :: Developers
Classifier: License :: OSI Approved :: MIT License
Classifier: Operating System :: OS Independent
Classifier: Programming Language :: Python
Classifier: Programming Language :: Python :: 3 :: Only
Classifier: Programming Language :: Python :: 3.11
Classifier: Topic :: Software Development :: Libraries :: Python Modules
Requires-Python: >=3.11
Requires-Dist: httpx>=0.25.0
Requires-Dist: rdflib>=7.0.0
Requires-Dist: rich>=13.5.0
Requires-Dist: typer>=0.9.0
Provides-Extra: dev
Requires-Dist: coverage>=7.8.0; extra == 'dev'
Requires-Dist: mypy>=1.5.0; extra == 'dev'
Requires-Dist: pytest-asyncio>=0.21.1; extra == 'dev'
Requires-Dist: pytest-cov>=6.0.0; extra == 'dev'
Requires-Dist: pytest>=7.4.0; extra == 'dev'
Requires-Dist: ruff>=0.1.0; extra == 'dev'
